{"1":{"count":8.0,"name":"горох","unit":"стручков","id":1},"2":{"count":8.0,"name":"горох","unit":"стручков","id":2},"3":{"count":8.0,"name":"горох","unit":"стручков","id":3},"4":{"count":1.0,"name":"соль","unit":"по вкусу","id":4},"5":{"count":2.0,"name":"Пиво","unit":"л.","id":5},"6":{"count":8.0,"name":"горох","unit":"стручков","id":6},"7":{"count":500.0,"name":"курица","unit":"грамм ","id":7},"8":{"count":1.0,"name":"Лимон","unit":"штука","id":8},"9":{"count":200.0,"name":"Сахар","unit":"грамм","id":9}}орох","unit":"стручков","id":2},"3":{"count":8.0,"name":"горох","unit":"стручков","id":3},"4":{"count":1.0,"name":"соль","unit":"по вкусу","id":4},"5":{"count":2.0,"name":"Пиво","unit":"л.","id":5},"6":{"count":8.0,"name":"горох","unit":"стручков","id":6},"7":{"count":500.0,"name":"курица","unit":"грамм ","id":7},"8":{"count":1.0,"name":"Лимо